Workbook

Sheet START HERE
B2: HOME BAKERY PRICING & PROFIT CALCULATOR
B3: Singapore Edition — 2026
B5: Cost your bakes accurately — ingredients, packaging, labour and overhead — then price for real profit instead of guessing.
B7: WHAT THIS CALCULATOR DOES
B8: INGREDIENTS tab — build your ingredient database: what you bought, how much it cost, and the cost per gram/ml/unit.
B9: RECIPE COSTING — pick a recipe and enter quantities used; the sheet prices every ingredient line and totals the batch.
B10: LABOUR & OVERHEAD — add your time value, utilities and equipment allowance; allocate them per batch and per item.
B11: PRICING & PROFIT — see cost per item, suggested price at your target margin, profit per item and batch, and a monthly profit projection.
B12: UPGRADE SCENARIO — compare today's home operation against a shared-kitchen setup with higher overheads, and see what sales volume or pricing keeps your target margin.
B14: HOW TO USE IT — 4 STEPS
B15: STEP 1 · INGREDIENTS: enter each ingredient you buy — package size, unit and price. The sheet computes cost per usable unit automatically.
B16: STEP 2 · RECIPE COSTING: choose one recipe (the example uses a classic butter cookie batch). Enter quantity used per ingredient — costs flow in from the database.
... B29: © SGEventsHub · Singapore Home Bakery Pricing & Profit Calculator (2026) · v2026.1

Sheet INGREDIENTS
B1: INGREDIENT DATABASE
B2: Enter each ingredient you actually buy. Cost-per-usable-unit calculates automatically. Recipe Costing pulls prices from here.
B3: Ingredient | C3: Package size | D3: Unit | E3: Package price | F3: Cost per unit (auto) | G3: Notes / brand
B4: Plain flour | C4: 1 | D4: kg | E4: 2.35 | F4: =IF(D4="kg",E4/(C4*1000),IF(D4="L",E4/(C4*1000),IF(E4=0,"",E4/C4))) -> 0 | G4: e.g., Prima — NTUC
B5: Butter (salted) | C5: 250 | D5: g | E5: 3.75 | F5: =IF(D5="kg",E5/(C5*1000),IF(D5="L",E5/(C5*1000),IF(E5=0,"",E5/C5))) -> 0 | G5: e.g., SCS block
B6: Icing sugar | C6: 500 | D6: g | E6: 2.8 | F6: =IF(D6="kg",E6/(C6*1000),IF(D6="L",E6/(C6*1000),IF(E6=0,"",E6/C6))) -> 0 | G6: Fine grade
B7: Brown sugar | C7: 500 | D7: g | E7: 2.55 | F7: =IF(D7="kg",E7/(C7*1000),IF(D7="L",E7/(C7*1000),IF(E7=0,"",E7/C7))) -> 0 | G7: Soft brown
B8: Eggs | C8: 10 | D8: pcs | E8: 3.2 | F8: =IF(D8="kg",E8/(C8*1000),IF(D8="L",E8/(C8*1000),IF(E8=0,"",E8/C8))) -> 0 | G8: Grade A, tray of 10
B9: Vanilla extract | C9: 50 | D9: ml | E9: 6.9 | F9: =IF(D9="kg",E9/(C9*1000),IF(D9="L",E9/(C9*1000),IF(E9=0,"",E9/C9))) -> 0 | G9: Pure extract
B10: Baking powder | C10: 200 | D10: g | E10: 2.4 | F10: =IF(D10="kg",E10/(C10*1000),IF(D10="L",E10/(C10*1000),IF(E10=0,"",E10/C10))) -> 0 | G10: Double acting
B11: Salt | C11: 500 | D11: g | E11: 0.95 | F11: =IF(D11="kg",E11/(C11*1000),IF(D11="L",E11/(C11*1000),IF(E11=0,"",E11/C11))) -> 0 | G11: Table salt
B12: Chocolate chips | C12: 340 | D12: g | E12: 5.85 | F12: =IF(D12="kg",E12/(C12*1000),IF(D12="L",E12/(C12*1000),IF(E12=0,"",E12/C12))) -> 0 | G12: Dark, baking chips
B13: Full-fat milk | C13: 1 | D13: L | E13: 3.45 | F13: =IF(D13="kg",E13/(C13*1000),IF(D13="L",E13/(C13*1000),IF(E13=0,"",E13/C13))) -> 0 | G13: Fresh, UHT ok
F14: =IF($D14="kg",$E14/($C14*1000),IF($D14="L",$E14/($C14*1000),IF($E14=0,"",$E14/$C14)))
F15: =IF($D15="kg",$E15/($C15*1000),IF($D15="L",$E15/($C15*1000),IF($E15=0,"",$E15/$C15)))
F16: =IF($D16="kg",$E16/($C16*1000),IF($D16="L",$E16/($C16*1000),IF($E16=0,"",$E16/$C16)))
F17: =IF($D17="kg",$E17/($C17*1000),IF($D17="L",$E17/($C17*1000),IF($E17=0,"",$E17/$C17)))
F18: =IF($D18="kg",$E18/($C18*1000),IF($D18="L",$E18/($C18*1000),IF($E18=0,"",$E18/$C18)))
F19: =IF($D19="kg",$E19/($C19*1000),IF($D19="L",$E19/($C19*1000),IF($E19=0,"",$E19/$C19)))
F20: =IF($D20="kg",$E20/($C20*1000),IF($D20="L",$E20/($C20*1000),IF($E20=0,"",$E20/$C20)))
F21: =IF($D21="kg",$E21/($C21*1000),IF($D21="L",$E21/($C21*1000),IF($E21=0,"",$E21/$C21)))
F22: =IF($D22="kg",$E22/($C22*1000),IF($D22="L",$E22/($C22*1000),IF($E22=0,"",$E22/$C22)))
F23: =IF($D23="kg",$E23/($C23*1000),IF($D23="L",$E23/($C23*1000),IF($E23=0,"",$E23/$C23)))
F24: =IF($D24="kg",$E24/($C24*1000),IF($D24="L",$E24/($C24*1000),IF($E24=0,"",$E24/$C24)))
F25: =IF($D25="kg",$E25/($C25*1000),IF($D25="L",$E25/($C25*1000),IF($E25=0,"",$E25/$C25)))
... F27: =IF($D27="kg",$E27/($C27*1000),IF($D27="L",$E27/($C27*1000),IF($E27=0,"",$E27/$C27)))
B29: How cost-per-unit works: kg and L are converted to g and ml respectively (÷1000 factor), then price ÷ converted size. Units like pcs divide directly. Add more ingredients in the blank rows.

Sheet RECIPE COSTING
B1: RECIPE COSTING
B2: Example recipe: Classic Butter Cookies (24 pieces). Enter quantity used — line costs pull from the INGREDIENTS database.
B3: Ingredient | C3: Qty used | D3: Unit | E3: Line cost (auto) | F3: % of ingredient cost | G3: Notes
B4: Plain flour | C4: 300 | D4: g | E4: =$C4*'INGREDIENTS'!F4 -> 0 | F4: =IF($E$10=0,"",E4/$E$10)
B5: Butter (salted) | C5: 200 | D5: g | E5: =$C5*'INGREDIENTS'!F5 -> 0 | F5: =IF($E$10=0,"",E5/$E$10)
B6: Icing sugar | C6: 100 | D6: g | E6: =$C6*'INGREDIENTS'!F6 -> 0 | F6: =IF($E$10=0,"",E6/$E$10)
B7: Eggs | C7: 1 | D7: pcs | E7: =$C7*'INGREDIENTS'!F8 -> 0 | F7: =IF($E$10=0,"",E7/$E$10)
B8: Vanilla extract | C8: 5 | D8: ml | E8: =$C8*'INGREDIENTS'!F9 -> 0 | F8: =IF($E$10=0,"",E8/$E$10)
B9: Salt | C9: 2 | D9: g | E9: =$C9*'INGREDIENTS'!F11 -> 0 | F9: =IF($E$10=0,"",E9/$E$10)
B10: TOTAL INGREDIENT COST | E10: =SUM(E4:E9) -> 0
B12: PACKAGING & YIELD
B13: Batch yield (pieces) | C13: 24
B14: Packaging cost per piece | C14: 0.25
B15: Packaging cost per batch (auto) | C15: =C13*C14 -> 0
B17: Named cells used downstream: TOTAL INGREDIENT COST (E10), Yield (C13), Packaging/batch (C15). LABOUR & OVERHEAD adds the rest.

Sheet LABOUR & OVERHEAD
B1: LABOUR, UTILITIES & OVERHEAD
B2: Pay yourself properly. These costs are allocated per batch and per item on PRICING & PROFIT.
B4: YOUR TIME
B5: Your target hourly rate | C5: 18 | D5: What an hour of your skilled baking time should earn.
B6: Hours per batch (prep+bake+clean) | C6: 2.5 | D6: Be honest — include washing up and cooling time.
B7: UTILITIES PER BATCH
B8: Electricity / gas per batch | C8: 2.8 | D8: Oven + mixer + hob estimate. Split monthly bill by batches baked.
B9: MONTHLY OVERHEAD (ALLOCATED)
B10: Equipment depreciation / month | C10: 25 | D10: Mixer, oven, tins ÷ useful months. Example: S$900 gear over 36 months ≈ S$25.
B11: Other overheads / month | C11: 30 | D11: Packaging stock storage, listing fees, samples, etc.
B12: Batches you bake per month | C12: 20 | D12: Used to split monthly overhead across batches.
B14: CALCULATED ALLOCATIONS
B15: Labour cost per batch | C15: =C5*C6 -> 0 | D15: Hourly rate × hours per batch.
B16: Monthly overhead total | C16: =C10+C11 -> 0 | D16: Equipment + other recurring overheads.
B17: Overhead allocated per batch | C17: =IF(C12=0,0,C16/C12) -> 0 | D17: Monthly overhead ÷ batches per month. Guarded against divide-by-zero.
B18: Utilities + overhead per batch | C18: =C8+C17 -> 0 | D18: Added on top of labour when costing a batch.

Sheet PRICING & PROFIT
B1: PRICING, MARGIN & MONTHLY PROFIT
B2: All values flow from RECIPE COSTING and LABOUR & OVERHEAD. Only yellow cells are editable.
B4: FULL BATCH COST
B5: Ingredients per batch | C5: ='RECIPE COSTING'!E10 -> 0
B6: Packaging per batch | C6: ='RECIPE COSTING'!C15 -> 0
B7: Labour per batch | C7: ='LABOUR & OVERHEAD'!C15 -> 0
B8: Utilities + overhead per batch | C8: ='LABOUR & OVERHEAD'!C18 -> 0
B9: TOTAL COST PER BATCH | C9: =C5+C6+C7+C8 -> 0
B10: Pieces per batch | C10: ='RECIPE COSTING'!C13 -> 0
B11: COST PER ITEM | C11: =IF(C10=0,0,C9/C10) -> 0
B13: SET YOUR PRICE
B14: Target gross margin | C14: 0.45 | D14: 45% means cost is 55% of price. Typical home-bakery range: 40–60%.
B15: Suggested price per item | C15: =IF(C11=0,0,C11/(1-C14)) -> 0 | D15: Cost ÷ (1 − margin).
B16: Your chosen price per item | C16: 4.5 | D16: What you will actually charge (round for the market).
B17: Gross profit per item | C17: =C16-C11 -> 0
B18: Margin at your price | C18: =IF(C16=0,0,(C16-C11)/C16) -> 0
B20: BATCH & MONTHLY PROJECTION
B21: Profit per batch | C21: =(C16-C11)*C10 -> 0
B22: Items sold per month | C22: 240
B23: Batches needed per month | C23: =IF(C10=0,0,ROUNDUP(C22/C10,0)) -> 0
B24: PROJECTED MONTHLY PROFIT | C24: =(C16-C11)*C22 -> 0
B25: Projected monthly revenue | C25: =C16*C22 -> 0
B27: =IF(C18<0.3,"⚠ Your margin is below 30% — most home bakeries need 40%+ to survive fees, wastage and slow weeks.","Margin looks workable — remember platform/payment fees (~2–4%) come out of this.")

Sheet UPGRADE SCENARIO
B1: SHARED-KITCHEN UPGRADE SCENARIO
B2: Compare today's home operation vs renting shared-kitchen hours. What volume or price keeps your target margin?
B3: SCENARIO INPUTS
B4: Home: full cost per item (from Pricing) | C4: ='PRICING & PROFIT'!C11 -> 0
B5: Shared kitchen hourly rate | C5: 25 | D5: Typical SG shared/commercial kitchens: S$20–40/hr.
B6: Extra hours needed per batch | C6: 1.5 | D6: Load-in, load-out, compliance cleaning.
B7: Shared kitchen fixed monthly fee | C7: 150 | D7: Locker/storage/membership if applicable.
B8: Planned batches per month (upgraded) | C8: 24
B9: Target margin (same as Pricing) | C9: ='PRICING & PROFIT'!C14 -> 0
B11: SCENARIO COMPARISON
B12: Scenario | C12: Cost/item | D12: Break-even items/month | E12: Notes
B13: A · Home (current) | C13: ='PRICING & PROFIT'!C11 -> 0 | D13: =IF(AND('PRICING & PROFIT'!C16-C13>0,'LABOUR & OVERHEAD'!C16>0),'LABOUR & OVERHEAD'!C16/('PRICING & PROFIT'!C16-C13),"n/a") | E13: Items/month to cover your monthly overheads at your chosen price.
B14: B · Shared kitchen | C14: =C13+C5*C6/MAX(1,'RECIPE COSTING'!13)+C7/MAX(1,C8*'RECIPE COSTING'!13) -> 0 | D14: =IF(('PRICING & PROFIT'!C16-C14)<=0,"price too low",(C7+'LABOUR & OVERHEAD'!C16)/('PRICING & PROFIT'!C16-C14)) | E14: Adds hourly cost spread per item + fixed fee spread across planned output.
B16: =IF(C14>='PRICING & PROFIT'!C16,"Upgrade NOT viable at current price — raise price or negotiate kitchen rates.",IF(C14<='PRICING & PROFIT'!C16*(1-C9),"Upgrade CAN hold your target margin at current price.","Upgrade possible but margin shrinks below target — needs higher price or volume."))

Sheet SOURCES & NOTES
B1: SOURCES, ASSUMPTIONS & NOTES
B2: Official references and assumption disclosures for this calculator.
B3: Regulatory Context (verify current rules)
B4: • SFA — Home-Based Food Businesses guidance (small-scale, for household income): https://www.sfa.gov.sg/
B5: • URA/HDB — home use rules for private residential and HDB premises; no employment of external staff for HDB home businesses.
B6: • NEA — environmental hygiene expectations for food preparation at home.
B7: • IRAS — income from side businesses may be taxable; keep records. https://www.iras.gov.sg/
B8: • Rules evolve — always confirm on official portals before scaling up.
B10: Pricing Assumptions Used
B11: • Ingredient prices: typical Singapore supermarket (NTUC FairPrice) shelf prices, 2026 examples.
B12: • Labour rate default S$18/hr — a placeholder for YOUR opportunity cost; adjust freely.
B13: • Utilities per batch estimated from typical domestic oven usage (~S$2.50–3.00).
... B27: • Profit projections assume steady demand; real months vary.
