Workbook

Sheet START HERE
B2: Singapore PR Readiness & Document Audit 2026
B3: A practical planning tool to organise your PR application documents, track readiness, and identify gaps — NOT a prediction of approval.
B5: WHAT THIS WORKBOOK DOES
B6: • PROFILE — capture your background details (years in SG, employment, family status, etc.) for quick reference.
B7: • DOCUMENT CHECKLIST — list every required and supporting document, mark status (Done / Missing / N/A), add notes.
B8: • READINESS SCORE — automatic tally of required items vs completed, with a simple status indicator.
B9: • ACTION PLAN — auto-generates a prioritised list of missing items with recommended actions.
B11: HOW TO USE — 3 STEPS
B12: STEP 1 · Go to PROFILE and fill in your details.
B13: STEP 2 · Go to DOCUMENT CHECKLIST. For each item, set Status to Done / Missing / N/A and add notes.
B14: STEP 3 · Review READINESS SCORE and ACTION PLAN. Focus on high-priority missing items first.
B16: WHAT IS OFFICIAL vs PLANNING GUIDANCE vs USER INPUT
... B24: Yellow = editable input · Green = auto-calculated · Do not type into green cells.

Sheet PROFILE
B2: STEP 1 · YOUR PROFILE
B3: Fill in the yellow cells. This sheet is for your reference and does not drive calculations.
B5: PERSONAL DETAILS
B6: Full name (as in passport)
B7: Date of birth
B8: Nationality
B9: Current FIN / NRIC (if any)
B10: Marital status
B11: Spouse name (if married)
B12: Spouse nationality
B13: Children (names, DOB, nationality)
B15: SINGAPORE HISTORY
B16: Date of first entry to Singapore
B17: Total years in Singapore (continuous) | C17: 0
B18: Current pass type (EP / S Pass / WP / DP / LTVP / PR / Citizen)
B19: Previous pass types held
B20: Any previous PR application? | C20: No
B21: If yes, year and outcome
B23: EMPLOYMENT & INCOME
B24: Current employer
B25: Occupation / Job title
B26: Industry
B27: Monthly basic salary (S$) | C27: 0
B28: Monthly variable/bonus (S$) | C28: 0
B29: Annual bonus (months) | C29: 0
B30: CPF contribution (monthly, S$) | C30: 0
B31: Years with current employer | C31: 0
B32: Previous employer (if < 2 years current)
B34: EDUCATION
B35: Highest qualification
B36: Institution
B37: Country of institution
B38: Year of graduation
B39: Professional certifications / memberships

Sheet DOCUMENT CHECKLIST
B2: STEP 2 · DOCUMENT CHECKLIST
B3: For each item, set Status (Done / Missing / N/A) in column F. Add notes in column G. Yellow = editable.
B5: # | C5: Document / Item | D5: Category | E5: Required? | F5: Status | G5: Notes
B6: 1 | C6: Valid passport (bio-data page) | D6: Identity & Civil | E6: Yes
B7: 2 | C7: Birth certificate | D7: Identity & Civil | E7: Yes
B8: 3 | C8: Marriage certificate (if married) | D8: Identity & Civil | E8: No
B9: 4 | C9: Divorce decree / death cert of spouse (if applicable) | D9: Identity & Civil | E9: No
B10: 5 | C10: Children's birth certificates | D10: Identity & Civil | E10: No
B11: 6 | C11: Spouse's passport (if married) | D11: Identity & Civil | E11: No
B12: 7 | C12: National ID card (home country) | D12: Identity & Civil | E12: No
B13: 8 | C13: Change of name deed poll (if applicable) | D13: Identity & Civil | E13: No
B14: 9 | C14: Current pass (EP / S Pass / WP / DP / LTVP) copy | D14: Immigration & Pass | E14: Yes
B15: 10 | C15: Previous pass copies (if any) | D15: Immigration & Pass | E15: No
B16: 11 | C16: Entry permit / approval letters | D16: Immigration & Pass | E16: No
B17: 12 | C17: Travel history (ICA e-service printout) | D17: Immigration & Pass | E17: No
... B45: 40 | C45: Any other relevant documents | D45: Supporting | E45: No

Sheet READINESS SCORE
B2: READINESS SCORE
B3: Auto-calculates from DOCUMENT CHECKLIST. Green = calculated. Do not edit.
B5: SUMMARY
B6: Total required items | C6: =COUNTIF('DOCUMENT CHECKLIST'!E6:E45,"Yes") -> 0
B7: Completed (Done) | C7: =COUNTIFS('DOCUMENT CHECKLIST'!E6:E45,"Yes",'DOCUMENT CHECKLIST'!F6:F45,"Done") -> 0
B8: Missing | C8: =COUNTIFS('DOCUMENT CHECKLIST'!E6:E45,"Yes",'DOCUMENT CHECKLIST'!F6:F45,"Missing") -> 0
B9: Marked N/A | C9: =COUNTIFS('DOCUMENT CHECKLIST'!E6:E45,"Yes",'DOCUMENT CHECKLIST'!F6:F45,"N/A") -> 0
B11: READINESS % (Done ÷ Required) | C11: =IF(COUNTIF('DOCUMENT CHECKLIST'!E6:E45,"Yes")=0,0,COUNTIFS('DOCUMENT CHECKLIST'!E6:E45,"Yes",'DOCUMENT CHECKLIST'!F6:F45,"Done")/COUNTIF('DOCUMENT CHECKLIST'!E6:E45,"Yes")) -> 0
B13: STATUS INDICATOR
B14: Overall status | C14: =IF(IF(COUNTIF('DOCUMENT CHECKLIST'!E6:E45,"Yes")=0,0,COUNTIFS('DOCUMENT CHECKLIST'!E6:E45,"Yes",'DOCUMENT CHECKLIST'!F6:F45,"Done")/COUNTIF('DOCUMENT CHECKLIST'!E6:E45,"Yes"))=1,"Ready for review",IF(IF(COUNTIF('DOCUMENT CHECKLIST'!E6:E45,"Yes")=0,0,COUNTIFS('DOCUMENT CHECKLIST'!E6:E45,"Yes",'DOCUMENT CHECKLIST'!F6:F45,"Done")/COUNTIF('DOCUMENT CHECKLIST'!E6:E45,"Yes"))>=0.7,"Needs attention","Not ready")) -> 0
B16: BREAKDOWN BY CATEGORY
B17: Category | C17: Required | D17: Done | E17: Missing | F17: N/A | G17: % Done
B18: Identity & Civil | C18: =COUNTIFS('DOCUMENT CHECKLIST'!D6:D45,"Identity & Civil",'DOCUMENT CHECKLIST'!E6:E45,"Yes") -> 0 | D18: =COUNTIFS('DOCUMENT CHECKLIST'!D6:D45,"Identity & Civil",'DOCUMENT CHECKLIST'!E6:E45,"Yes",'DOCUMENT CHECKLIST'!F6:F45,"Done") -> 0 | E18: =COUNTIFS('DOCUMENT CHECKLIST'!D6:D45,"Identity & Civil",'DOCUMENT CHECKLIST'!E6:E45,"Yes",'DOCUMENT CHECKLIST'!F6:F45,"Missing") -> 0 | F18: =COUNTIFS('DOCUMENT CHECKLIST'!D6:D45,"Identity & Civil",'DOCUMENT CHECKLIST'!E6:E45,"Yes",'DOCUMENT CHECKLIST'!F6:F45,"N/A") -> 0 | G18: =IF(COUNTIFS('DOCUMENT CHECKLIST'!D6:D45,"Identity & Civil",'DOCUMENT CHECKLIST'!E6:E45,"Yes")=0,0,COUNTIFS('DOCUMENT CHECKLIST'!D6:D45,"Identity & Civil",'DOCUMENT CHECKLIST'!E6:E45,"Yes",'DOCUMENT CHECKLIST'!F6:F45,"Done")/COUNTIFS('DOCUMENT CHECKLIST'!D6:D45,"Identity & Civil",'DOCUMENT CHECKLIST'!E6:E45,"Yes")) -> 0
B19: Immigration & Pass | C19: =COUNTIFS('DOCUMENT CHECKLIST'!D6:D45,"Immigration & Pass",'DOCUMENT CHECKLIST'!E6:E45,"Yes") -> 0 | D19: =COUNTIFS('DOCUMENT CHECKLIST'!D6:D45,"Immigration & Pass",'DOCUMENT CHECKLIST'!E6:E45,"Yes",'DOCUMENT CHECKLIST'!F6:F45,"Done") -> 0 | E19: =COUNTIFS('DOCUMENT CHECKLIST'!D6:D45,"Immigration & Pass",'DOCUMENT CHECKLIST'!E6:E45,"Yes",'DOCUMENT CHECKLIST'!F6:F45,"Missing") -> 0 | F19: =COUNTIFS('DOCUMENT CHECKLIST'!D6:D45,"Immigration & Pass",'DOCUMENT CHECKLIST'!E6:E45,"Yes",'DOCUMENT CHECKLIST'!F6:F45,"N/A") -> 0 | G19: =IF(COUNTIFS('DOCUMENT CHECKLIST'!D6:D45,"Immigration & Pass",'DOCUMENT CHECKLIST'!E6:E45,"Yes")=0,0,COUNTIFS('DOCUMENT CHECKLIST'!D6:D45,"Immigration & Pass",'DOCUMENT CHECKLIST'!E6:E45,"Yes",'DOCUMENT CHECKLIST'!F6:F45,"Done")/COUNTIFS('DOCUMENT CHECKLIST'!D6:D45,"Immigration & Pass",'DOCUMENT CHECKLIST'!E6:E45,"Yes")) -> 0
B20: Employment | C20: =COUNTIFS('DOCUMENT CHECKLIST'!D6:D45,"Employment",'DOCUMENT CHECKLIST'!E6:E45,"Yes") -> 0 | D20: =COUNTIFS('DOCUMENT CHECKLIST'!D6:D45,"Employment",'DOCUMENT CHECKLIST'!E6:E45,"Yes",'DOCUMENT CHECKLIST'!F6:F45,"Done") -> 0 | E20: =COUNTIFS('DOCUMENT CHECKLIST'!D6:D45,"Employment",'DOCUMENT CHECKLIST'!E6:E45,"Yes",'DOCUMENT CHECKLIST'!F6:F45,"Missing") -> 0 | F20: =COUNTIFS('DOCUMENT CHECKLIST'!D6:D45,"Employment",'DOCUMENT CHECKLIST'!E6:E45,"Yes",'DOCUMENT CHECKLIST'!F6:F45,"N/A") -> 0 | G20: =IF(COUNTIFS('DOCUMENT CHECKLIST'!D6:D45,"Employment",'DOCUMENT CHECKLIST'!E6:E45,"Yes")=0,0,COUNTIFS('DOCUMENT CHECKLIST'!D6:D45,"Employment",'DOCUMENT CHECKLIST'!E6:E45,"Yes",'DOCUMENT CHECKLIST'!F6:F45,"Done")/COUNTIFS('DOCUMENT CHECKLIST'!D6:D45,"Employment",'DOCUMENT CHECKLIST'!E6:E45,"Yes")) -> 0
B21: Income & Financial | C21: =COUNTIFS('DOCUMENT CHECKLIST'!D6:D45,"Income & Financial",'DOCUMENT CHECKLIST'!E6:E45,"Yes") -> 0 | D21: =COUNTIFS('DOCUMENT CHECKLIST'!D6:D45,"Income & Financial",'DOCUMENT CHECKLIST'!E6:E45,"Yes",'DOCUMENT CHECKLIST'!F6:F45,"Done") -> 0 | E21: =COUNTIFS('DOCUMENT CHECKLIST'!D6:D45,"Income & Financial",'DOCUMENT CHECKLIST'!E6:E45,"Yes",'DOCUMENT CHECKLIST'!F6:F45,"Missing") -> 0 | F21: =COUNTIFS('DOCUMENT CHECKLIST'!D6:D45,"Income & Financial",'DOCUMENT CHECKLIST'!E6:E45,"Yes",'DOCUMENT CHECKLIST'!F6:F45,"N/A") -> 0 | G21: =IF(COUNTIFS('DOCUMENT CHECKLIST'!D6:D45,"Income & Financial",'DOCUMENT CHECKLIST'!E6:E45,"Yes")=0,0,COUNTIFS('DOCUMENT CHECKLIST'!D6:D45,"Income & Financial",'DOCUMENT CHECKLIST'!E6:E45,"Yes",'DOCUMENT CHECKLIST'!F6:F45,"Done")/COUNTIFS('DOCUMENT CHECKLIST'!D6:D45,"Income & Financial",'DOCUMENT CHECKLIST'!E6:E45,"Yes")) -> 0
B22: Education | C22: =COUNTIFS('DOCUMENT CHECKLIST'!D6:D45,"Education",'DOCUMENT CHECKLIST'!E6:E45,"Yes") -> 0 | D22: =COUNTIFS('DOCUMENT CHECKLIST'!D6:D45,"Education",'DOCUMENT CHECKLIST'!E6:E45,"Yes",'DOCUMENT CHECKLIST'!F6:F45,"Done") -> 0 | E22: =COUNTIFS('DOCUMENT CHECKLIST'!D6:D45,"Education",'DOCUMENT CHECKLIST'!E6:E45,"Yes",'DOCUMENT CHECKLIST'!F6:F45,"Missing") -> 0 | F22: =COUNTIFS('DOCUMENT CHECKLIST'!D6:D45,"Education",'DOCUMENT CHECKLIST'!E6:E45,"Yes",'DOCUMENT CHECKLIST'!F6:F45,"N/A") -> 0 | G22: =IF(COUNTIFS('DOCUMENT CHECKLIST'!D6:D45,"Education",'DOCUMENT CHECKLIST'!E6:E45,"Yes")=0,0,COUNTIFS('DOCUMENT CHECKLIST'!D6:D45,"Education",'DOCUMENT CHECKLIST'!E6:E45,"Yes",'DOCUMENT CHECKLIST'!F6:F45,"Done")/COUNTIFS('DOCUMENT CHECKLIST'!D6:D45,"Education",'DOCUMENT CHECKLIST'!E6:E45,"Yes")) -> 0
B23: Family | C23: =COUNTIFS('DOCUMENT CHECKLIST'!D6:D45,"Family",'DOCUMENT CHECKLIST'!E6:E45,"Yes") -> 0 | D23: =COUNTIFS('DOCUMENT CHECKLIST'!D6:D45,"Family",'DOCUMENT CHECKLIST'!E6:E45,"Yes",'DOCUMENT CHECKLIST'!F6:F45,"Done") -> 0 | E23: =COUNTIFS('DOCUMENT CHECKLIST'!D6:D45,"Family",'DOCUMENT CHECKLIST'!E6:E45,"Yes",'DOCUMENT CHECKLIST'!F6:F45,"Missing") -> 0 | F23: =COUNTIFS('DOCUMENT CHECKLIST'!D6:D45,"Family",'DOCUMENT CHECKLIST'!E6:E45,"Yes",'DOCUMENT CHECKLIST'!F6:F45,"N/A") -> 0 | G23: =IF(COUNTIFS('DOCUMENT CHECKLIST'!D6:D45,"Family",'DOCUMENT CHECKLIST'!E6:E45,"Yes")=0,0,COUNTIFS('DOCUMENT CHECKLIST'!D6:D45,"Family",'DOCUMENT CHECKLIST'!E6:E45,"Yes",'DOCUMENT CHECKLIST'!F6:F45,"Done")/COUNTIFS('DOCUMENT CHECKLIST'!D6:D45,"Family",'DOCUMENT CHECKLIST'!E6:E45,"Yes")) -> 0
B24: Supporting | C24: =COUNTIFS('DOCUMENT CHECKLIST'!D6:D45,"Supporting",'DOCUMENT CHECKLIST'!E6:E45,"Yes") -> 0 | D24: =COUNTIFS('DOCUMENT CHECKLIST'!D6:D45,"Supporting",'DOCUMENT CHECKLIST'!E6:E45,"Yes",'DOCUMENT CHECKLIST'!F6:F45,"Done") -> 0 | E24: =COUNTIFS('DOCUMENT CHECKLIST'!D6:D45,"Supporting",'DOCUMENT CHECKLIST'!E6:E45,"Yes",'DOCUMENT CHECKLIST'!F6:F45,"Missing") -> 0 | F24: =COUNTIFS('DOCUMENT CHECKLIST'!D6:D45,"Supporting",'DOCUMENT CHECKLIST'!E6:E45,"Yes",'DOCUMENT CHECKLIST'!F6:F45,"N/A") -> 0 | G24: =IF(COUNTIFS('DOCUMENT CHECKLIST'!D6:D45,"Supporting",'DOCUMENT CHECKLIST'!E6:E45,"Yes")=0,0,COUNTIFS('DOCUMENT CHECKLIST'!D6:D45,"Supporting",'DOCUMENT CHECKLIST'!E6:E45,"Yes",'DOCUMENT CHECKLIST'!F6:F45,"Done")/COUNTIFS('DOCUMENT CHECKLIST'!D6:D45,"Supporting",'DOCUMENT CHECKLIST'!E6:E45,"Yes")) -> 0
B26: Note: Only "Required = Yes" items count toward the readiness score.
B27: Optional items (Required = No) are for tracking only.

Sheet ACTION PLAN
B2: ACTION PLAN — MISSING ITEMS PRIORITISED
B3: Auto-generates from DOCUMENT CHECKLIST where Status = Missing and Required = Yes.
B5: # | C5: Missing Document / Item | D5: Category | E5: Recommended Action | F5: Priority | G5: Target Date | H5: Notes
B6: 1 | C6: =IF(AND('DOCUMENT CHECKLIST'!E6="Yes",'DOCUMENT CHECKLIST'!F6="Missing"),'DOCUMENT CHECKLIST'!C6,"") -> 0 | D6: =IF(AND('DOCUMENT CHECKLIST'!E6="Yes",'DOCUMENT CHECKLIST'!F6="Missing"),'DOCUMENT CHECKLIST'!D6,"") -> 0 | E6: =IF(AND('DOCUMENT CHECKLIST'!E6="Yes",'DOCUMENT CHECKLIST'!F6="Missing"),CHOOSE(MATCH('DOCUMENT CHECKLIST'!D6,{"Identity & Civil","Immigration & Pass","Employment","Income & Financial","Education","Family","Supporting"},0),"Obtain from ICA/home country authority","Request from employer/HR/ICA portal","Request from employer/HR","Download from IRAS/CPF/Bank portals","Obtain from institution","Coordinate with family members","Prepare at your discretion"),"") -> 0 | F6: =IF(AND('DOCUMENT CHECKLIST'!E6="Yes",'DOCUMENT CHECKLIST'!F6="Missing"),VLOOKUP('DOCUMENT CHECKLIST'!D6,{"Identity & Civil","High";"Immigration & Pass","High";"Employment","High";"Income & Financial","High";"Education","Medium";"Family","Medium";"Supporting","Low"},2,FALSE),"") -> 0
B7: 2 | C7: =IF(AND('DOCUMENT CHECKLIST'!E7="Yes",'DOCUMENT CHECKLIST'!F7="Missing"),'DOCUMENT CHECKLIST'!C7,"") -> 0 | D7: =IF(AND('DOCUMENT CHECKLIST'!E7="Yes",'DOCUMENT CHECKLIST'!F7="Missing"),'DOCUMENT CHECKLIST'!D7,"") -> 0 | E7: =IF(AND('DOCUMENT CHECKLIST'!E7="Yes",'DOCUMENT CHECKLIST'!F7="Missing"),CHOOSE(MATCH('DOCUMENT CHECKLIST'!D7,{"Identity & Civil","Immigration & Pass","Employment","Income & Financial","Education","Family","Supporting"},0),"Obtain from ICA/home country authority","Request from employer/HR/ICA portal","Request from employer/HR","Download from IRAS/CPF/Bank portals","Obtain from institution","Coordinate with family members","Prepare at your discretion"),"") -> 0 | F7: =IF(AND('DOCUMENT CHECKLIST'!E7="Yes",'DOCUMENT CHECKLIST'!F7="Missing"),VLOOKUP('DOCUMENT CHECKLIST'!D7,{"Identity & Civil","High";"Immigration & Pass","High";"Employment","High";"Income & Financial","High";"Education","Medium";"Family","Medium";"Supporting","Low"},2,FALSE),"") -> 0
B8: 3 | C8: =IF(AND('DOCUMENT CHECKLIST'!E8="Yes",'DOCUMENT CHECKLIST'!F8="Missing"),'DOCUMENT CHECKLIST'!C8,"") -> 0 | D8: =IF(AND('DOCUMENT CHECKLIST'!E8="Yes",'DOCUMENT CHECKLIST'!F8="Missing"),'DOCUMENT CHECKLIST'!D8,"") -> 0 | E8: =IF(AND('DOCUMENT CHECKLIST'!E8="Yes",'DOCUMENT CHECKLIST'!F8="Missing"),CHOOSE(MATCH('DOCUMENT CHECKLIST'!D8,{"Identity & Civil","Immigration & Pass","Employment","Income & Financial","Education","Family","Supporting"},0),"Obtain from ICA/home country authority","Request from employer/HR/ICA portal","Request from employer/HR","Download from IRAS/CPF/Bank portals","Obtain from institution","Coordinate with family members","Prepare at your discretion"),"") -> 0 | F8: =IF(AND('DOCUMENT CHECKLIST'!E8="Yes",'DOCUMENT CHECKLIST'!F8="Missing"),VLOOKUP('DOCUMENT CHECKLIST'!D8,{"Identity & Civil","High";"Immigration & Pass","High";"Employment","High";"Income & Financial","High";"Education","Medium";"Family","Medium";"Supporting","Low"},2,FALSE),"") -> 0
B9: 4 | C9: =IF(AND('DOCUMENT CHECKLIST'!E9="Yes",'DOCUMENT CHECKLIST'!F9="Missing"),'DOCUMENT CHECKLIST'!C9,"") -> 0 | D9: =IF(AND('DOCUMENT CHECKLIST'!E9="Yes",'DOCUMENT CHECKLIST'!F9="Missing"),'DOCUMENT CHECKLIST'!D9,"") -> 0 | E9: =IF(AND('DOCUMENT CHECKLIST'!E9="Yes",'DOCUMENT CHECKLIST'!F9="Missing"),CHOOSE(MATCH('DOCUMENT CHECKLIST'!D9,{"Identity & Civil","Immigration & Pass","Employment","Income & Financial","Education","Family","Supporting"},0),"Obtain from ICA/home country authority","Request from employer/HR/ICA portal","Request from employer/HR","Download from IRAS/CPF/Bank portals","Obtain from institution","Coordinate with family members","Prepare at your discretion"),"") -> 0 | F9: =IF(AND('DOCUMENT CHECKLIST'!E9="Yes",'DOCUMENT CHECKLIST'!F9="Missing"),VLOOKUP('DOCUMENT CHECKLIST'!D9,{"Identity & Civil","High";"Immigration & Pass","High";"Employment","High";"Income & Financial","High";"Education","Medium";"Family","Medium";"Supporting","Low"},2,FALSE),"") -> 0
B10: 5 | C10: =IF(AND('DOCUMENT CHECKLIST'!E10="Yes",'DOCUMENT CHECKLIST'!F10="Missing"),'DOCUMENT CHECKLIST'!C10,"") -> 0 | D10: =IF(AND('DOCUMENT CHECKLIST'!E10="Yes",'DOCUMENT CHECKLIST'!F10="Missing"),'DOCUMENT CHECKLIST'!D10,"") -> 0 | E10: =IF(AND('DOCUMENT CHECKLIST'!E10="Yes",'DOCUMENT CHECKLIST'!F10="Missing"),CHOOSE(MATCH('DOCUMENT CHECKLIST'!D10,{"Identity & Civil","Immigration & Pass","Employment","Income & Financial","Education","Family","Supporting"},0),"Obtain from ICA/home country authority","Request from employer/HR/ICA portal","Request from employer/HR","Download from IRAS/CPF/Bank portals","Obtain from institution","Coordinate with family members","Prepare at your discretion"),"") -> 0 | F10: =IF(AND('DOCUMENT CHECKLIST'!E10="Yes",'DOCUMENT CHECKLIST'!F10="Missing"),VLOOKUP('DOCUMENT CHECKLIST'!D10,{"Identity & Civil","High";"Immigration & Pass","High";"Employment","High";"Income & Financial","High";"Education","Medium";"Family","Medium";"Supporting","Low"},2,FALSE),"") -> 0
B11: 6 | C11: =IF(AND('DOCUMENT CHECKLIST'!E11="Yes",'DOCUMENT CHECKLIST'!F11="Missing"),'DOCUMENT CHECKLIST'!C11,"") -> 0 | D11: =IF(AND('DOCUMENT CHECKLIST'!E11="Yes",'DOCUMENT CHECKLIST'!F11="Missing"),'DOCUMENT CHECKLIST'!D11,"") -> 0 | E11: =IF(AND('DOCUMENT CHECKLIST'!E11="Yes",'DOCUMENT CHECKLIST'!F11="Missing"),CHOOSE(MATCH('DOCUMENT CHECKLIST'!D11,{"Identity & Civil","Immigration & Pass","Employment","Income & Financial","Education","Family","Supporting"},0),"Obtain from ICA/home country authority","Request from employer/HR/ICA portal","Request from employer/HR","Download from IRAS/CPF/Bank portals","Obtain from institution","Coordinate with family members","Prepare at your discretion"),"") -> 0 | F11: =IF(AND('DOCUMENT CHECKLIST'!E11="Yes",'DOCUMENT CHECKLIST'!F11="Missing"),VLOOKUP('DOCUMENT CHECKLIST'!D11,{"Identity & Civil","High";"Immigration & Pass","High";"Employment","High";"Income & Financial","High";"Education","Medium";"Family","Medium";"Supporting","Low"},2,FALSE),"") -> 0
B12: 7 | C12: =IF(AND('DOCUMENT CHECKLIST'!E12="Yes",'DOCUMENT CHECKLIST'!F12="Missing"),'DOCUMENT CHECKLIST'!C12,"") -> 0 | D12: =IF(AND('DOCUMENT CHECKLIST'!E12="Yes",'DOCUMENT CHECKLIST'!F12="Missing"),'DOCUMENT CHECKLIST'!D12,"") -> 0 | E12: =IF(AND('DOCUMENT CHECKLIST'!E12="Yes",'DOCUMENT CHECKLIST'!F12="Missing"),CHOOSE(MATCH('DOCUMENT CHECKLIST'!D12,{"Identity & Civil","Immigration & Pass","Employment","Income & Financial","Education","Family","Supporting"},0),"Obtain from ICA/home country authority","Request from employer/HR/ICA portal","Request from employer/HR","Download from IRAS/CPF/Bank portals","Obtain from institution","Coordinate with family members","Prepare at your discretion"),"") -> 0 | F12: =IF(AND('DOCUMENT CHECKLIST'!E12="Yes",'DOCUMENT CHECKLIST'!F12="Missing"),VLOOKUP('DOCUMENT CHECKLIST'!D12,{"Identity & Civil","High";"Immigration & Pass","High";"Employment","High";"Income & Financial","High";"Education","Medium";"Family","Medium";"Supporting","Low"},2,FALSE),"") -> 0
B13: 8 | C13: =IF(AND('DOCUMENT CHECKLIST'!E13="Yes",'DOCUMENT CHECKLIST'!F13="Missing"),'DOCUMENT CHECKLIST'!C13,"") -> 0 | D13: =IF(AND('DOCUMENT CHECKLIST'!E13="Yes",'DOCUMENT CHECKLIST'!F13="Missing"),'DOCUMENT CHECKLIST'!D13,"") -> 0 | E13: =IF(AND('DOCUMENT CHECKLIST'!E13="Yes",'DOCUMENT CHECKLIST'!F13="Missing"),CHOOSE(MATCH('DOCUMENT CHECKLIST'!D13,{"Identity & Civil","Immigration & Pass","Employment","Income & Financial","Education","Family","Supporting"},0),"Obtain from ICA/home country authority","Request from employer/HR/ICA portal","Request from employer/HR","Download from IRAS/CPF/Bank portals","Obtain from institution","Coordinate with family members","Prepare at your discretion"),"") -> 0 | F13: =IF(AND('DOCUMENT CHECKLIST'!E13="Yes",'DOCUMENT CHECKLIST'!F13="Missing"),VLOOKUP('DOCUMENT CHECKLIST'!D13,{"Identity & Civil","High";"Immigration & Pass","High";"Employment","High";"Income & Financial","High";"Education","Medium";"Family","Medium";"Supporting","Low"},2,FALSE),"") -> 0
B14: 9 | C14: =IF(AND('DOCUMENT CHECKLIST'!E14="Yes",'DOCUMENT CHECKLIST'!F14="Missing"),'DOCUMENT CHECKLIST'!C14,"") -> 0 | D14: =IF(AND('DOCUMENT CHECKLIST'!E14="Yes",'DOCUMENT CHECKLIST'!F14="Missing"),'DOCUMENT CHECKLIST'!D14,"") -> 0 | E14: =IF(AND('DOCUMENT CHECKLIST'!E14="Yes",'DOCUMENT CHECKLIST'!F14="Missing"),CHOOSE(MATCH('DOCUMENT CHECKLIST'!D14,{"Identity & Civil","Immigration & Pass","Employment","Income & Financial","Education","Family","Supporting"},0),"Obtain from ICA/home country authority","Request from employer/HR/ICA portal","Request from employer/HR","Download from IRAS/CPF/Bank portals","Obtain from institution","Coordinate with family members","Prepare at your discretion"),"") -> 0 | F14: =IF(AND('DOCUMENT CHECKLIST'!E14="Yes",'DOCUMENT CHECKLIST'!F14="Missing"),VLOOKUP('DOCUMENT CHECKLIST'!D14,{"Identity & Civil","High";"Immigration & Pass","High";"Employment","High";"Income & Financial","High";"Education","Medium";"Family","Medium";"Supporting","Low"},2,FALSE),"") -> 0
B15: 10 | C15: =IF(AND('DOCUMENT CHECKLIST'!E15="Yes",'DOCUMENT CHECKLIST'!F15="Missing"),'DOCUMENT CHECKLIST'!C15,"") -> 0 | D15: =IF(AND('DOCUMENT CHECKLIST'!E15="Yes",'DOCUMENT CHECKLIST'!F15="Missing"),'DOCUMENT CHECKLIST'!D15,"") -> 0 | E15: =IF(AND('DOCUMENT CHECKLIST'!E15="Yes",'DOCUMENT CHECKLIST'!F15="Missing"),CHOOSE(MATCH('DOCUMENT CHECKLIST'!D15,{"Identity & Civil","Immigration & Pass","Employment","Income & Financial","Education","Family","Supporting"},0),"Obtain from ICA/home country authority","Request from employer/HR/ICA portal","Request from employer/HR","Download from IRAS/CPF/Bank portals","Obtain from institution","Coordinate with family members","Prepare at your discretion"),"") -> 0 | F15: =IF(AND('DOCUMENT CHECKLIST'!E15="Yes",'DOCUMENT CHECKLIST'!F15="Missing"),VLOOKUP('DOCUMENT CHECKLIST'!D15,{"Identity & Civil","High";"Immigration & Pass","High";"Employment","High";"Income & Financial","High";"Education","Medium";"Family","Medium";"Supporting","Low"},2,FALSE),"") -> 0
B16: 11 | C16: =IF(AND('DOCUMENT CHECKLIST'!E16="Yes",'DOCUMENT CHECKLIST'!F16="Missing"),'DOCUMENT CHECKLIST'!C16,"") -> 0 | D16: =IF(AND('DOCUMENT CHECKLIST'!E16="Yes",'DOCUMENT CHECKLIST'!F16="Missing"),'DOCUMENT CHECKLIST'!D16,"") -> 0 | E16: =IF(AND('DOCUMENT CHECKLIST'!E16="Yes",'DOCUMENT CHECKLIST'!F16="Missing"),CHOOSE(MATCH('DOCUMENT CHECKLIST'!D16,{"Identity & Civil","Immigration & Pass","Employment","Income & Financial","Education","Family","Supporting"},0),"Obtain from ICA/home country authority","Request from employer/HR/ICA portal","Request from employer/HR","Download from IRAS/CPF/Bank portals","Obtain from institution","Coordinate with family members","Prepare at your discretion"),"") -> 0 | F16: =IF(AND('DOCUMENT CHECKLIST'!E16="Yes",'DOCUMENT CHECKLIST'!F16="Missing"),VLOOKUP('DOCUMENT CHECKLIST'!D16,{"Identity & Civil","High";"Immigration & Pass","High";"Employment","High";"Income & Financial","High";"Education","Medium";"Family","Medium";"Supporting","Low"},2,FALSE),"") -> 0
B17: 12 | C17: =IF(AND('DOCUMENT CHECKLIST'!E17="Yes",'DOCUMENT CHECKLIST'!F17="Missing"),'DOCUMENT CHECKLIST'!C17,"") -> 0 | D17: =IF(AND('DOCUMENT CHECKLIST'!E17="Yes",'DOCUMENT CHECKLIST'!F17="Missing"),'DOCUMENT CHECKLIST'!D17,"") -> 0 | E17: =IF(AND('DOCUMENT CHECKLIST'!E17="Yes",'DOCUMENT CHECKLIST'!F17="Missing"),CHOOSE(MATCH('DOCUMENT CHECKLIST'!D17,{"Identity & Civil","Immigration & Pass","Employment","Income & Financial","Education","Family","Supporting"},0),"Obtain from ICA/home country authority","Request from employer/HR/ICA portal","Request from employer/HR","Download from IRAS/CPF/Bank portals","Obtain from institution","Coordinate with family members","Prepare at your discretion"),"") -> 0 | F17: =IF(AND('DOCUMENT CHECKLIST'!E17="Yes",'DOCUMENT CHECKLIST'!F17="Missing"),VLOOKUP('DOCUMENT CHECKLIST'!D17,{"Identity & Civil","High";"Immigration & Pass","High";"Employment","High";"Income & Financial","High";"Education","Medium";"Family","Medium";"Supporting","Low"},2,FALSE),"") -> 0
... B45: 40 | C45: =IF(AND('DOCUMENT CHECKLIST'!E45="Yes",'DOCUMENT CHECKLIST'!F45="Missing"),'DOCUMENT CHECKLIST'!C45,"") -> 0 | D45: =IF(AND('DOCUMENT CHECKLIST'!E45="Yes",'DOCUMENT CHECKLIST'!F45="Missing"),'DOCUMENT CHECKLIST'!D45,"") -> 0 | E45: =IF(AND('DOCUMENT CHECKLIST'!E45="Yes",'DOCUMENT CHECKLIST'!F45="Missing"),CHOOSE(MATCH('DOCUMENT CHECKLIST'!D45,{"Identity & Civil","Immigration & Pass","Employment","Income & Financial","Education","Family","Supporting"},0),"Obtain from ICA/home country authority","Request from employer/HR/ICA portal","Request from employer/HR","Download from IRAS/CPF/Bank portals","Obtain from institution","Coordinate with family members","Prepare at your discretion"),"") -> 0 | F45: =IF(AND('DOCUMENT CHECKLIST'!E45="Yes",'DOCUMENT CHECKLIST'!F45="Missing"),VLOOKUP('DOCUMENT CHECKLIST'!D45,{"Identity & Civil","High";"Immigration & Pass","High";"Employment","High";"Income & Financial","High";"Education","Medium";"Family","Medium";"Supporting","Low"},2,FALSE),"") -> 0
B58: PRIORITY COUNTS
B59: High priority missing | C59: =COUNTIF(F6:F55,"High") -> 0
B60: Medium priority missing | C60: =COUNTIF(F6:F55,"Medium") -> 0
B61: Low priority missing | C61: =COUNTIF(F6:F55,"Low") -> 0
