Workbook

Sheet START HERE
B2: SINGAPORE CAR vs MRT + GRAB
B3: Total Cost Decision Calculator — 2026 Edition
B5: Enter your own transport habits, car costs and assumptions. Compare your estimated 1-year and 10-year cost before making a major financial commitment.
B6: WHAT THIS CALCULATOR DOES
B7: It estimates what YOU would personally spend on getting around Singapore under three scenarios:
B8: Scenario A — MRT / bus only Scenario B — MRT / bus + Grab / taxi Scenario C — owning a car
B9: …and shows each scenario side by side over 1 year and 10 years, plus a break-even point: how high your Grab / taxi spending would need to go before a car becomes cost-comparable.
B11: WHO IT IS FOR
B12: Singapore residents who spend significant money on transport and are asking: “Does owning a car actually make sense for MY household?” Ideal if you may buy a car within the next 1–3 years, or you already drive and want to see the full picture.
B14: HOW TO USE IT — 3 STEPS
B15: STEP 1 · Enter your assumptions on the INPUTS tab (edit the yellow cells only).
B16: STEP 2 · Review your estimated monthly, 1-year and 10-year costs on the COMPARISON tab.
... B26: © SGEventsHub · Singapore Car vs MRT/Grab Decision Calculator (2026) · v2026.1

Sheet INPUTS
B1: STEP 1 · ENTER YOUR ASSUMPTIONS
B2: Edit ONLY the yellow cells. Pre-filled values are realistic 2026 examples — replace them with your own numbers.
B4: PUBLIC TRANSPORT (SCENARIO A)
B5: Monthly MRT / bus cost | C5: 120 | D5: Example: a commuter paying fares or holding a travel card. Replace with your own average.
B6: GRAB / TAXI (ADDED IN SCENARIO B)
B7: Monthly Grab / taxi spending | C7: 300 | D7: Example includes weekday rides and occasional late-night trips.
B8: CAR — ONE-OFF COSTS & FINANCING
B9: Car purchase price | C9: 70000 | D9: Example price for the vehicle itself, before COE.
B10: COE / upfront ownership cost | C10: 95000 | D10: Example: COE premium plus registration, parcel fees and extras. Check current COE results yourself.
B11: Loan amount | C11: 70000 | D11: Amount you expect to borrow. Enter 0 if paying cash.
B12: Loan monthly payment | C12: 1330 | D12: Example: 5-year flat-rate car loan. Confirm rates with lenders.
B13: CAR — MONTHLY RUNNING COSTS
B14: Petrol per month | C14: 250 | D14: Example for moderate mileage. Adjust for your driving distance and fuel prices.
B15: Parking per month | C15: 250 | D15: Example combines residential season parking with occasional town parking.
B16: ERP per month | C16: 80 | D16: Example for a commute that passes pricing gantries a few times a week.
B17: Insurance per month | C17: 200 | D17: Example annual premium of about S$2,400 divided across the year.
B18: Maintenance / servicing per month | C18: 150 | D18: Regular servicing, tyres and wear-and-tear, averaged monthly.
B19: Other monthly car costs | C19: 50 | D19: Road tax, car washes, accessories — anything else recurring.
B20: DEPRECIATION
B21: Estimated annual depreciation | C21: 12000 | D21: How much value the car loses per year. This is usually the single largest hidden cost.
B23: Upfront cash needed (calculated) | C23: =INPUTS!C9+INPUTS!C10-INPUTS!C11 -> 95000 | D23: Purchase price + COE/upfront cost − loan. Informational only.

Sheet COMPARISON
B1: STEP 2 · REVIEW YOUR ESTIMATED COSTS
B2: Everything here updates automatically from the INPUTS tab — change an input and come straight back.
B4: Scenario | C4: Per month | D4: Per 1 year | E4: Per 10 years
B5: Scenario A · MRT / bus only | C5: =INPUTS!C5 -> 120 | D5: =INPUTS!C5*12 -> 1440 | E5: =INPUTS!C5*120 -> 14400
B6: Scenario B · MRT / bus + Grab / taxi | C6: =INPUTS!C5+INPUTS!C7 -> 420 | D6: =(INPUTS!C5+INPUTS!C7)*12 -> 5040 | E6: =(INPUTS!C5+INPUTS!C7)*120 -> 50400
B7: Scenario C · Car ownership — Monthly Cash Outflow | C7: =INPUTS!C12+INPUTS!C14+INPUTS!C15+INPUTS!C16+INPUTS!C17+INPUTS!C18+INPUTS!C19 -> NaN | D7: =(INPUTS!C12+INPUTS!C14+INPUTS!C15+INPUTS!C16+INPUTS!C17+INPUTS!C18+INPUTS!C19)*12 -> NaN | E7: =(INPUTS!C12+INPUTS!C14+INPUTS!C15+INPUTS!C16+INPUTS!C17+INPUTS!C18+INPUTS!C19)*120 -> NaN
B8: Scenario C · Car ownership — Monthly Economic Cost | C8: =INPUTS!C12+INPUTS!C14+INPUTS!C15+INPUTS!C16+INPUTS!C17+INPUTS!C18+INPUTS!C19+INPUTS!C21/12 -> 3310 | D8: =(INPUTS!C12+INPUTS!C14+INPUTS!C15+INPUTS!C16+INPUTS!C17+INPUTS!C18+INPUTS!C19+INPUTS!C21/12)*12 -> 39720 | E8: =(INPUTS!C12+INPUTS!C14+INPUTS!C15+INPUTS!C16+INPUTS!C17+INPUTS!C18+INPUTS!C19+INPUTS!C21/12)*120 -> 397200
B9: Monthly Cash Outflow = loan payment + petrol + parking + ERP + insurance + maintenance + other costs (excludes depreciation). Monthly Economic Cost = Cash Outflow + depreciation (annual ÷ 12). Upfront cash outlay is shown on the INPUTS tab — read both together before deciding.
B11: DIFFERENCE BETWEEN SCENARIOS
B12: Adding Grab / taxi (B − A) | C12: =INPUTS!C7 -> 300 | D12: =INPUTS!C7*12 -> 3600 | E12: =INPUTS!C7*120 -> 36000
B13: Owning a car instead of MRT + Grab (Economic Cost − B) | C13: =C8-C6 -> 2890 | D13: =D8-D6 -> 34680 | E13: =E8-E6 -> 346800
B14: Car Cash Outflow vs MRT + Grab (Cash Outflow − B) | C14: =C7-C6 -> NaN | D14: =D7-D6 -> NaN | E14: =E7-E6 -> NaN
B15: Relative cost — car Economic Cost ÷ MRT + Grab | C15: =IF(C6>0,C8/C6,"n/a") -> 7.8809524 | D15: =IF(D6>0,D8/D6,"n/a") -> 7.8809524 | E15: =IF(E6>0,E8/E6,"n/a") -> 7.8809524
B16: WHICH SCENARIO IS CHEAPER FOR YOU?
B17: Overall verdict (Economic Cost) | C17: =IF(C8>C6,"Under your current assumptions, MRT + Grab is CHEAPER than owning a car (Economic Cost).","Under your current assumptions, owning a car is CHEAPER than MRT + Grab (Economic Cost).") -> Under your current assumptions, MRT + Grab is CHEAPER than owning a car (Economic Cost).
B18: ="At your assumed Grab / taxi spend, a car (Economic Cost) costs about "&TEXT(MAX(0,C8-C6),"S$#,##0")&" more (or less) per month than MRT + Grab. Cash Outflow difference: "&TEXT(MAX(0,C7-C6),"S$#,##0") -> At your assumed Grab / taxi spend, a car (Economic Cost) costs about S$2,890 more (or less) per month than MRT + Grab. Cash Outflow difference: S$NaN
B20: Tip: Compare Economic Cost (includes depreciation) for true cost of ownership. Cash Outflow shows actual monthly cash spending. Upfront cash required is on the INPUTS tab.

Sheet SCENARIO ANALYSIS
B1: STEP 3 · STRESS-TEST YOUR ASSUMPTIONS
B2: Change the yellow INPUTS and watch every figure update instantly. The tools below answer “what would have to change?”
B4: BREAK-EVEN ANALYSIS — HOW HIGH WOULD YOUR GRAB BILL HAVE TO GO?
B5: Your current monthly Grab / taxi spend (from INPUTS) | C5: =INPUTS!C7 -> 300 | D5: Editable on the INPUTS tab.
B6: Break-even monthly Grab / taxi spend | C6: =MAX(0,(INPUTS!C12+INPUTS!C14+INPUTS!C15+INPUTS!C16+INPUTS!C17+INPUTS!C18+INPUTS!C19+INPUTS!C21/12)-INPUTS!C5) -> 3190 | D6: The Grab / taxi bill at which MRT + Grab would cost the same as owning a car under your assumptions.
B7: What this means for you | C7: =IF(INPUTS!C7>=MAX(0,(INPUTS!C12+INPUTS!C14+INPUTS!C15+INPUTS!C16+INPUTS!C17+INPUTS!C18+INPUTS!C19+INPUTS!C21/12)-INPUTS!C5),"Your Grab / taxi spending is AT or ABOVE break-even — under your assumptions, a car may be financially rational.","A car only becomes cost-comparable if your monthly Grab / taxi spend rises to the break-even level above.") -> A car only becomes cost-comparable if your monthly Grab / taxi spend rises to the break-even level above.
B9: SENSITIVITY — MONTHLY ECONOMIC COST (INCLUDES DEPRECIATION)
B10: Annual depreciation ↓ / Petrol → | C10: 150 | D10: 250 | E10: 350
B11: 6000 | C11: =INPUTS!C12+INPUTS!C15+INPUTS!C16+INPUTS!C17+INPUTS!C18+INPUTS!C19+$B11/12+C$10 -> 2710 | D11: =INPUTS!C12+INPUTS!C15+INPUTS!C16+INPUTS!C17+INPUTS!C18+INPUTS!C19+$B11/12+D$10 -> 2810 | E11: =INPUTS!C12+INPUTS!C15+INPUTS!C16+INPUTS!C17+INPUTS!C18+INPUTS!C19+$B11/12+E$10 -> 2910
B12: 9000 | C12: =INPUTS!C12+INPUTS!C15+INPUTS!C16+INPUTS!C17+INPUTS!C18+INPUTS!C19+$B12/12+C$10 -> 2960 | D12: =INPUTS!C12+INPUTS!C15+INPUTS!C16+INPUTS!C17+INPUTS!C18+INPUTS!C19+$B12/12+D$10 -> 3060 | E12: =INPUTS!C12+INPUTS!C15+INPUTS!C16+INPUTS!C17+INPUTS!C18+INPUTS!C19+$B12/12+E$10 -> 3160
B13: 12000 | C13: =INPUTS!C12+INPUTS!C15+INPUTS!C16+INPUTS!C17+INPUTS!C18+INPUTS!C19+$B13/12+C$10 -> 3210 | D13: =INPUTS!C12+INPUTS!C15+INPUTS!C16+INPUTS!C17+INPUTS!C18+INPUTS!C19+$B13/12+D$10 -> 3310 | E13: =INPUTS!C12+INPUTS!C15+INPUTS!C16+INPUTS!C17+INPUTS!C18+INPUTS!C19+$B13/12+E$10 -> 3410
B14: 15000 | C14: =INPUTS!C12+INPUTS!C15+INPUTS!C16+INPUTS!C17+INPUTS!C18+INPUTS!C19+$B14/12+C$10 -> 3460 | D14: =INPUTS!C12+INPUTS!C15+INPUTS!C16+INPUTS!C17+INPUTS!C18+INPUTS!C19+$B14/12+D$10 -> 3560 | E14: =INPUTS!C12+INPUTS!C15+INPUTS!C16+INPUTS!C17+INPUTS!C18+INPUTS!C19+$B14/12+E$10 -> 3660
B15: 18000 | C15: =INPUTS!C12+INPUTS!C15+INPUTS!C16+INPUTS!C17+INPUTS!C18+INPUTS!C19+$B15/12+C$10 -> 3710 | D15: =INPUTS!C12+INPUTS!C15+INPUTS!C16+INPUTS!C17+INPUTS!C18+INPUTS!C19+$B15/12+D$10 -> 3810 | E15: =INPUTS!C12+INPUTS!C15+INPUTS!C16+INPUTS!C17+INPUTS!C18+INPUTS!C19+$B15/12+E$10 -> 3910
B16: Each cell is the Monthly Economic Cost (Cash Outflow + depreciation) of owning a car for that combination of annual depreciation and petrol spend (all other inputs stay as entered on the INPUTS tab). Compare with your monthly MRT + Grab total on the COMPARISON tab.
B18: SENSITIVITY — MONTHLY CASH OUTFLOW (EXCLUDES DEPRECIATION)
B19: Annual depreciation (not in cash outflow) ↓ / Petrol → | C19: 150 | D19: 250 | E19: 350
B20: 6000 | C20: =INPUTS!C12+INPUTS!C15+INPUTS!C16+INPUTS!C17+INPUTS!C18+INPUTS!C19+C$19 -> 2210 | D20: =INPUTS!C12+INPUTS!C15+INPUTS!C16+INPUTS!C17+INPUTS!C18+INPUTS!C19+D$19 -> 2310 | E20: =INPUTS!C12+INPUTS!C15+INPUTS!C16+INPUTS!C17+INPUTS!C18+INPUTS!C19+E$19 -> 2410
B21: 9000 | C21: =INPUTS!C12+INPUTS!C15+INPUTS!C16+INPUTS!C17+INPUTS!C18+INPUTS!C19+C$19 -> 2210 | D21: =INPUTS!C12+INPUTS!C15+INPUTS!C16+INPUTS!C17+INPUTS!C18+INPUTS!C19+D$19 -> 2310 | E21: =INPUTS!C12+INPUTS!C15+INPUTS!C16+INPUTS!C17+INPUTS!C18+INPUTS!C19+E$19 -> 2410
B22: 12000 | C22: =INPUTS!C12+INPUTS!C15+INPUTS!C16+INPUTS!C17+INPUTS!C18+INPUTS!C19+C$19 -> 2210 | D22: =INPUTS!C12+INPUTS!C15+INPUTS!C16+INPUTS!C17+INPUTS!C18+INPUTS!C19+D$19 -> 2310 | E22: =INPUTS!C12+INPUTS!C15+INPUTS!C16+INPUTS!C17+INPUTS!C18+INPUTS!C19+E$19 -> 2410
B23: 15000 | C23: =INPUTS!C12+INPUTS!C15+INPUTS!C16+INPUTS!C17+INPUTS!C18+INPUTS!C19+C$19 -> 2210 | D23: =INPUTS!C12+INPUTS!C15+INPUTS!C16+INPUTS!C17+INPUTS!C18+INPUTS!C19+D$19 -> 2310 | E23: =INPUTS!C12+INPUTS!C15+INPUTS!C16+INPUTS!C17+INPUTS!C18+INPUTS!C19+E$19 -> 2410
B24: 18000 | C24: =INPUTS!C12+INPUTS!C15+INPUTS!C16+INPUTS!C17+INPUTS!C18+INPUTS!C19+C$19 -> 2210 | D24: =INPUTS!C12+INPUTS!C15+INPUTS!C16+INPUTS!C17+INPUTS!C18+INPUTS!C19+D$19 -> 2310 | E24: =INPUTS!C12+INPUTS!C15+INPUTS!C16+INPUTS!C17+INPUTS!C18+INPUTS!C19+E$19 -> 2410
B25: Each cell is the Monthly Cash Outflow (excludes depreciation) of owning a car. This represents actual monthly cash spending. Compare with your monthly MRT + Grab total on the COMPARISON tab to understand cash flow impact.
B27: TRY THESE QUICK EXPERIMENTS
B28: • Set your expected Grab / taxi spend to what you think you will really pay after buying a car — most households keep some ride-hailing use.
B29: • Test a pessimistic depreciation figure (cars depreciate fastest in the first years).
B30: • Add 20–30% to petrol and parking to see whether the verdict survives a bad year.
B31: • Change the loan payment to 0 to compare an all-cash purchase financed by your own money.
